Metadata-Version: 2.1
Name: pssq
Version: 0.0.2
Summary: Prepares PostgreSQL queries for execution in more useful Pythonic way. Not ORM.
Home-page: https://github.com/aptakhin/pssq
Author: Alexander Ptakhin
Author-email: me@aptakhin.name
License: MIT
Project-URL: Source Code, https://github.com/aptakhin/pssq
Keywords: pssq
Platform: UNKNOWN
Classifier: Development Status :: 3 - Alpha
Classifier: Intended Audience :: Developers
Classifier: License :: OSI Approved :: MIT License
Classifier: Programming Language :: Python
Classifier: Topic :: Software Development
